scipy_magic/__init__.py
scipy_magic/distributions.py
scipy_magic/kde.py
scipy_magic-1.0.0.dist-info/LICENSE
scipy_magic-1.0.0.dist-info/WHEEL
scipy_magic-1.0.0.dist-info/METADATA
scipy_magic-1.0.0.dist-info/RECORD
