Metadata-Version: 2.1
Name: scipy-magic
Version: 1.0.0
Summary: SciPy Magic
Home-page: https://github.com/tupui/scipy-magic
License: BSD-3-Clause
Keywords: scipy,ipython
Author: Pamphile Roy
Author-email: roy.pamphile@gmail.com
Requires-Python: >=3.8,<3.10
Classifier: License :: OSI Approved :: BSD License
Classifier: Programming Language :: Python :: 3
Classifier: Programming Language :: Python :: 3.8
Classifier: Programming Language :: Python :: 3.9
Requires-Dist: ipython (>=7.23.1,<8.0.0)
Requires-Dist: matplotlib (>=3.4.2,<4.0.0)
Requires-Dist: scipy (>=1.7.0,<2.0.0)
Project-URL: Repository, https://github.com/tupui/scipy-magic
